contd/__init__.py
contd/api/__init__.py
contd/api/dependencies.py
contd/api/grpc_service.py
contd/api/ledger_routes.py
contd/api/rate_limit.py
contd/api/routes.py
contd/api/server.py
contd/api/webhook_routes.py
contd/api/webhooks.py
contd/api/proto/workflow_pb2.py
contd/api/proto/workflow_pb2_grpc.py
contd/cli/__init__.py
contd/cli/config.py
contd/cli/main.py
contd/context/__init__.py
contd/context/health.py
contd/context/ledger.py
contd/context/recipes.py
contd/core/__init__.py
contd/core/engine.py
contd/core/idempotency.py
contd/core/recovery.py
contd/core/state_machine.py
contd/core/version.py
contd/models/__init__.py
contd/models/events.py
contd/models/savepoint.py
contd/models/serialization.py
contd/models/state.py
contd/observability/__init__.py
contd/observability/background.py
contd/observability/exporter.py
contd/observability/health.py
contd/observability/llm_metrics.py
contd/observability/logging.py
contd/observability/metrics.py
contd/observability/push.py
contd/observability/tracing.py
contd/persistence/__init__.py
contd/persistence/journal.py
contd/persistence/leases.py
contd/persistence/snapshots.py
contd/persistence/adapters/__init__.py
contd/persistence/adapters/factory.py
contd/persistence/adapters/postgres.py
contd/persistence/adapters/redis.py
contd/persistence/adapters/s3.py
contd/persistence/adapters/sqlite.py
contd/runtime/__init__.py
contd/runtime/context.py
contd/runtime/executor.py
contd/runtime/recovery.py
contd/sdk/__init__.py
contd/sdk/client.py
contd/sdk/context.py
contd/sdk/decorators.py
contd/sdk/errors.py
contd/sdk/llm.py
contd/sdk/recipes.py
contd/sdk/registry.py
contd/sdk/testing.py
contd/sdk/types.py
contd-0.1.5.dist-info/licenses/LICENSE
contd-0.1.5.dist-info/METADATA
contd-0.1.5.dist-info/WHEEL
contd-0.1.5.dist-info/entry_points.txt
contd-0.1.5.dist-info/top_level.txt
contd-0.1.5.dist-info/RECORD
