Metadata-Version: 2.4
Name: contd
Version: 0.1.5
Summary: Durable workflow execution engine with time-travel debugging
Author: Contd Team
License-Expression: LicenseRef-BSL-1.1
Project-URL: Homepage, https://github.com/bhavdeep98/contd.ai
Project-URL: Documentation, https://github.com/bhavdeep98/contd.ai/tree/main/docs
Project-URL: Repository, https://github.com/bhavdeep98/contd.ai
Keywords: workflow,durable,execution,time-travel,debugging
Classifier: Development Status :: 3 - Alpha
Classifier: Intended Audience :: Developers
Classifier: Programming Language :: Python :: 3
Classifier: Programming Language :: Python :: 3.10
Classifier: Programming Language :: Python :: 3.11
Classifier: Programming Language :: Python :: 3.12
Requires-Python: >=3.10
License-File: LICENSE
Requires-Dist: click>=8.0
Requires-Dist: requests>=2.28
Requires-Dist: fastapi>=0.100
Requires-Dist: uvicorn>=0.23
Requires-Dist: httpx>=0.24
Requires-Dist: pydantic>=2.0
Requires-Dist: jsonpatch>=1.33
Provides-Extra: postgres
Requires-Dist: psycopg2-binary>=2.9; extra == "postgres"
Provides-Extra: redis
Requires-Dist: redis>=4.0; extra == "redis"
Provides-Extra: s3
Requires-Dist: boto3>=1.26; extra == "s3"
Provides-Extra: observability
Requires-Dist: opentelemetry-api>=1.20; extra == "observability"
Requires-Dist: opentelemetry-sdk>=1.20; extra == "observability"
Requires-Dist: prometheus-client>=0.17; extra == "observability"
Requires-Dist: psutil>=5.9; extra == "observability"
Provides-Extra: all
Requires-Dist: contd[observability,postgres,redis,s3]; extra == "all"
Provides-Extra: dev
Requires-Dist: pytest>=7.0; extra == "dev"
Requires-Dist: pytest-asyncio>=0.21; extra == "dev"
Requires-Dist: pytest-cov>=4.0; extra == "dev"
Dynamic: license-file
